bombay/__init__.py
bombay/__main__.py
bombay/cli.py
bombay/templates.py
bombay/document_processing/__init__.py
bombay/document_processing/chunkers.py
bombay/document_processing/document.py
bombay/document_processing/loaders.py
bombay/evaluation/__init__.py
bombay/evaluation/metrics.py
bombay/pipeline/__init__.py
bombay/pipeline/embedding_models.py
bombay/pipeline/factory.py
bombay/pipeline/query_models.py
bombay/pipeline/rag_pipeline.py
bombay/pipeline/vector_db.py
bombay/plugins/__init__.py
bombay/plugins/custom_models.py
bombay/plugins/vector_db/__init__.py
bombay/plugins/vector_db/pgvector_db.py
bombay/plugins/vector_db/pinecone_db.py
bombay/utils/__init__.py
bombay/utils/config.py
bombay/utils/logging.py
bombay/utils/model_registry.py
bombay/utils/plugin_manager.py
bombay/utils/preprocessing.py
bombay/vector_db/__init__.py
bombay/vector_db/chroma_db.py
bombay/vector_db/hnswlib_db.py
bombay/vector_db/vector_db.py
bombay-1.0.0.dist-info/METADATA
bombay-1.0.0.dist-info/WHEEL
bombay-1.0.0.dist-info/top_level.txt
bombay-1.0.0.dist-info/RECORD
