Metadata-Version: 2.2
Name: bombay
Version: 1.0.0
Summary: RAG(Retrieval-Augmented Generation) 파이프라인을 쉽게 구축할 수 있는 Python 라이브러리
Home-page: https://github.com/bombay-ai/bombay
Author: Bombay Team
Author-email: info@bombay.ai
Classifier: Programming Language :: Python :: 3
Classifier: Programming Language :: Python :: 3.9
Classifier: Programming Language :: Python :: 3.10
Classifier: Programming Language :: Python :: 3.11
Classifier: License :: OSI Approved :: MIT License
Classifier: Operating System :: OS Independent
Classifier: Topic :: Scientific/Engineering :: Artificial Intelligence
Classifier: Topic :: Software Development :: Libraries :: Python Modules
Requires-Python: >=3.9
Requires-Dist: openai>=1.0.0
Requires-Dist: numpy>=1.20.0
Requires-Dist: pydantic>=2.10.0
Requires-Dist: pydantic-core>=2.27.0
Requires-Dist: httpx>=0.28.0
Requires-Dist: hnswlib>=0.7.0
Requires-Dist: chromadb>=0.4.0
Requires-Dist: python-dotenv>=1.0.0
Requires-Dist: pyfiglet>=0.8.0
Requires-Dist: rich>=13.0.0
Requires-Dist: scikit-learn>=1.0.0
Requires-Dist: beautifulsoup4>=4.10.0
Requires-Dist: markdown>=3.4.0
Requires-Dist: PyPDF2>=3.0.0
Requires-Dist: python-docx>=0.8.11
Requires-Dist: requests>=2.28.0
Requires-Dist: pyyaml>=6.0.0
Requires-Dist: bs4>=0.0.1
Requires-Dist: tqdm>=4.67.0
Provides-Extra: pinecone
Requires-Dist: pinecone-client>=2.2.0; extra == "pinecone"
Provides-Extra: pgvector
Requires-Dist: psycopg2-binary>=2.9.0; extra == "pgvector"
Provides-Extra: pdf
Requires-Dist: pymupdf>=1.20.0; extra == "pdf"
Provides-Extra: dev
Requires-Dist: pytest>=7.0.0; extra == "dev"
Requires-Dist: black>=23.0.0; extra == "dev"
Requires-Dist: isort>=5.12.0; extra == "dev"
Requires-Dist: mypy>=1.0.0; extra == "dev"
Provides-Extra: all
Requires-Dist: pinecone-client>=2.2.0; extra == "all"
Requires-Dist: psycopg2-binary>=2.9.0; extra == "all"
Requires-Dist: pymupdf>=1.20.0; extra == "all"
Dynamic: author
Dynamic: author-email
Dynamic: classifier
Dynamic: description
Dynamic: description-content-type
Dynamic: home-page
Dynamic: provides-extra
Dynamic: requires-dist
Dynamic: requires-python
Dynamic: summary
